hylink_mcp-1.0.6.dist-info/licenses/LICENSE
server/__init__.py
server/cdebug.py
server/common_tools.py
server/excel_read.py
server/mcp_sse.py
server/path_ls.py
server/weather_query.py
server/word_read.py
hylink_mcp-1.0.6.dist-info/METADATA
hylink_mcp-1.0.6.dist-info/WHEEL
hylink_mcp-1.0.6.dist-info/entry_points.txt
hylink_mcp-1.0.6.dist-info/top_level.txt
hylink_mcp-1.0.6.dist-info/RECORD
