Metadata-Version: 2.4
Name: hylink-mcp
Version: 1.0.6
Summary: mcp server some code
Author-email: haoyang <hao474798383@163.com>
License-Expression: Apache-2.0
Requires-Python: >=3.11
License-File: LICENSE
Requires-Dist: uvicorn>=0.32.1
Requires-Dist: python-dotenv>=1.0.0
Requires-Dist: requests>=2.31.0
Requires-Dist: gomyck-tools>=1.4.0
Requires-Dist: httpx[socks]>=0.28.1
Requires-Dist: mcp[cli]>=1.6.0
Requires-Dist: openpyxl>=3.1.5
Requires-Dist: pandas>=2.2.3
Requires-Dist: pyautogui>=0.9.54
Requires-Dist: pydantic>=2.11.3
Requires-Dist: python-docx>=1.1.2
Dynamic: license-file
